README
setup.cfg
setup.py
heatapp/__init__.py
heatapp/apiMethods.py
heatapp/apiRequest.py
heatapp/login.py
heatapp/sceneManager.py
heatapp/contracts/RoomStatusEnum.py
heatapp/contracts/ScenesEnum.py
heatapp/contracts/__init__.py
heatapp/contracts/credentials.py
heatapp/contracts/defaultApiParameters.py
heatapp/contracts/room.py
heatapp/contracts/scenes.py
heatapp/contracts/scenestatus.py
heatapp/contracts/userInfo.py
py_heatapp_de.egg-info/PKG-INFO
py_heatapp_de.egg-info/SOURCES.txt
py_heatapp_de.egg-info/dependency_links.txt
py_heatapp_de.egg-info/requires.txt
py_heatapp_de.egg-info/top_level.txt