Metadata-Version: 1.1
Name: py-heatapp-de
Version: 0.0.1.42
Summary: HeatApp local api integration library
Home-page: https://github.com/sfstar/py-heatapp-de
Author: Sven ten Raa
Author-email: sventenraa@gmail.com
License: GLPv3
Download-URL: https://github.com/sfstar/py-heatapp-de/archive/v0.0.1-alpha.tar.gz
Keywords: heatapp,api,integration
Platform: UNKNOWN
Classifier: Development Status :: 3 - Alpha
Classifier: Intended Audience :: Developers
Classifier: Topic :: Software Development :: Build Tools
Classifier: License :: OSI Approved :: GNU Affero General Public License v3 or later (AGPLv3+)
Classifier: Programming Language :: Python :: 3.9
